{
  "updated": "2026-06-10",
  "version": "0.2.0",
  "purpose": "Condensed repo snapshot: architecture, contracts, and integration status. Details in CONTRACTS.md, ARCHITECTURE.md, docs/PLATFORM_STATUS.md, plans/INTEGRATION_STATUS.md.",
  "canonical_docs": {
    "contracts": "CONTRACTS.md",
    "architecture": "ARCHITECTURE.md",
    "project_guide": "docs/PROJECT_GUIDE.md",
    "platform_status": "docs/PLATFORM_STATUS.md",
    "integration_status": "plans/INTEGRATION_STATUS.md",
    "examples": "examples/README.md",
    "backend_setup": "docs/BACKEND_SETUP.md"
  },
  "project_summary": "Backend agnostic manipulation runtime: one RoboEnv loop across MuJoCo, Gazebo, Isaac Sim, ROS2, and hardware. Tasks, sensor rigs, and policies bind via registry and YAML presets so simulator switches and sim2real paths share observation and action contracts.",
  "current_state": {
    "implemented": [
      "RoboEnv + Robot/RobotTask; from_config, presets, multi robot MuJoCo",
      "Backends: mujoco, gazebo, ros2_rviz, isaacsim (mock CI), real_world, dummy",
      "SensorRig + ObsPipeline (sync, noise, color blob → obs.objects); FT, IMU, contact, RGBD",
      "Policies: reach DSL, joint track, BC/PPO checkpoints, remote ZMQ/gRPC serve",
      "Training: Gymnasium adapter, SubprocVecEnv, robodeploy train bc|ppo|eval",
      "Benchmarks: manipulation_v1 harness, eval CLI, leaderboard JSON, train→eval E2E",
      "Safety: SafetyMonitor on step and reset; workspace, slew, force, e stop guards",
      "Sim2real: calibration CLIs, DR sweep, transfer eval (dummy tested paths)",
      "CI: ~620 tests (not hardware); live Gazebo pick E2E; package build workflow"
    ],
    "gaps": [
      "PyPI v0.2.0 tag not published",
      "Teleop / IL data collection stub only",
      "Gazebo pick CI ≥50% (target 70%); Isaac GPU parity unchecked live",
      "Benchmark tiers 2 to 8 placeholders; real hardware eval manual",
      "Tactile/lidar sensors not implemented"
    ],
    "verification": "pytest -m \"not hardware\": ~620 passed, ~19 skipped"
  },
  "key_decisions": [
    "Layers: IBackend, ITask, IPolicy, ISensor; shared types in core/types.py",
    "Robot + RobotTask per arm; not env wide task lists",
    "Sensors via registry pairs; policies read Observation, not get_prop_pose()",
    "Presets in examples/config/presets.yaml; examples/ not shipped on PyPI",
    "Safety and bind_runtime on reset are env responsibilities",
    "RoboBridge + seqlock for real hardware control vs inference split"
  ],
  "milestones": [
    {"phase": "v0.1 foundation", "summary": "Registry, backends, sensor rigs, obs pipeline, examples presets"},
    {"phase": "v0.2 Wave 2", "summary": "Training, benchmarks, safety, Gazebo E2E, docs, package CI (~65% of 12 goals)"},
    {"phase": "Next", "summary": "PyPI release, teleop datasets, Gazebo/Isaac parity, real hardware eval automation"}
  ],
  "recent": [
    "8bcef15 docs: fix README mermaid for GitHub",
    "5c2eaa8 docs: remove dashes from README prose",
    "7809376 docs: README sim2real and architecture overview",
    "a06e8b3 docs: comprehensive documentation pass v0.2",
    "2e8e137 fix: JointTrackPolicy config= target_qpos wiring"
  ]
}
